{
    "id":  "29404",
    "status":  "ok",
    "fetched_at":  "2026-06-10T23:43:23Z",
    "official_link":  null,
    "org_about":  null,
    "en":  {
               "lang":  "en",
               "title":  "JEES–Docomo International Student Scholarship for Graduate Students in Communications – Partial Funding",
               "sections":  [
                                {
                                    "header":  "Opportunity description",
                                    "body":  "\u003cdiv bis_skin_checked=\"1\"\u003e\u003cdiv bis_skin_checked=\"1\" class=\"description\"\u003e\u003cp data-end=\"556\" data-start=\"261\"\u003eSaitama University is a leading national university in Japan that offers undergraduate and graduate programs across a wide range of disciplines. The university is committed to supporting international students by providing various scholarships managed through its International Affairs Office.\u003c/p\u003e\u003cp data-end=\"989\" data-start=\"591\"\u003eThe \u003cstrong data-end=\"644\" data-start=\"595\"\u003eJEES\u0026ndash;Docomo International Student Scholarship\u003c/strong\u003e is offered to first-year master\u0026rsquo;s students who are international students specializing in information processing and communications, or fields that incorporate these areas into their research. The scholarship provides a monthly stipend of 120,000 JPY for up to two years and aims to support researchers dedicated to advancing this discipline.\u003c/p\u003e\u003ch3 data-end=\"1022\" data-start=\"996\"\u003e\u003cstrong\u003eApplication Deadline\u003c/strong\u003e\u003c/h3\u003e\u003cp data-end=\"1252\" data-start=\"1023\"\u003eThe application deadline is \u003cstrong data-end=\"1075\" data-start=\"1051\"\u003eApril 24 at 11:00 AM\u003c/strong\u003e. Applications must be submitted by email to the International Affairs Office along with the required documents, and applicants will receive feedback during the review period.\u003c/p\u003e\u003c/div\u003e\u003c/div\u003e"
                                },
                                {
                                    "header":  "Benefits",
                                    "body":  "\u003cul\u003e\u003cli data-end=\"1365\" data-start=\"1276\"\u003eA monthly stipend of \u003cstrong data-end=\"1312\" data-start=\"1297\"\u003e120,000 JPY\u003c/strong\u003e throughout the scholarship period (up to 2 years).\u003c/li\u003e\u003cli data-end=\"1463\" data-start=\"1368\"\u003eNo additional tuition fees; the scholarship directly supports the student\u0026rsquo;s academic program.\u003c/li\u003e\u003c/ul\u003e"
                                },
                                {
                                    "header":  "Eligibility criteria",
                                    "body":  "\u003cul\u003e\u003cli data-end=\"1543\" data-start=\"1499\"\u003eMust be a \u003cstrong data-end=\"1540\" data-start=\"1509\"\u003efirst-year master\u0026rsquo;s student\u003c/strong\u003e.\u003c/li\u003e\u003cli data-end=\"1636\" data-start=\"1546\"\u003eMust be a national of one of the eligible countries (Asia, Africa, South America, etc.).\u003c/li\u003e\u003cli data-end=\"1775\" data-start=\"1639\"\u003eThe applicant\u0026rsquo;s field of study must be related to information processing and communications, or use these areas within their research.\u003c/li\u003e\u003c/ul\u003e"
                                }
                            ]
           },
    "ar":  {
               "lang":  "ar",
               "title":  "منحة كاي دومو الدولية لطلاب الدراسات العليا في مجال الاتصالات – تمويل جزئي",
               "sections":  [
                                {
                                    "header":  "وصف الفرصة",
                                    "body":  "\u003cdiv bis_skin_checked=\"1\"\u003e\u003cdiv bis_skin_checked=\"1\" class=\"description_ar\"\u003e\u003cp data-end=\"507\" data-start=\"280\"\u003eجامعة سايتاما هي جامعة حكومية يابانية رائدة، تقدم برامج دراسات عليا وبكالوريوس في مجموعة واسعة من التخصصات. تعكس الجامعة التزامها بدعم الطلبة الدوليين من خلال توفير منح دراسية متنوعة تُدار من خلال مكتب الشؤون الدولية الخاص بها.\u003c/p\u003e\u003cp data-end=\"870\" data-start=\"535\"\u003eتُقدم مؤسسة \u0026quot;JEES・Docomo International Student Scholarship\u0026quot; منحة لطلاب المرحلة الأولى من الدراسات العليا (ماجستير)، مخصصة للطلاب الدوليين في مجال معالجة المعلومات والاتصالات أو التخصصات الداعمة التي تستخدم هذا المجال في بحثها. المنحة تُمنح شهريًا بقيمة 120,000 ين ياباني لمدة تصل إلى عامين، وتهدف إلى دعم الباحثين المهتمين بهذا التخصص.\u003c/p\u003e\u003ch3 data-end=\"905\" data-start=\"877\"\u003e\u003cstrong\u003eالموعد النهائي للتقديم\u003c/strong\u003e\u003c/h3\u003e\u003cp data-end=\"1105\" data-start=\"906\"\u003eيُغلق باب التقديم للمنحة في داخل الجامعة في يوم \u003cstrong data-end=\"986\" data-start=\"954\"\u003e24 أبريل الساعة 11:00 صباحًا\u003c/strong\u003e. يجب إرسال الطلب عبر البريد الإلكتروني إلى مكتب الشؤون الدولية مع رفع الوثائق المطلوبة، واستلام ردّ خلال فترة التقييم.\u003c/p\u003e\u003cp\u003e\u003cbr\u003e\u003c/p\u003e\u003c/div\u003e\u003c/div\u003e"
                                },
                                {
                                    "header":  "المنافع والفوائد",
                                    "body":  "\u003cdiv bis_skin_checked=\"1\"\u003e\u003cdiv bis_skin_checked=\"1\" class=\"benefits_ar\"\u003e\u003cul\u003e\u003cli data-end=\"1211\" data-start=\"1128\"\u003eدعم مالي قدره \u003cstrong data-end=\"1170\" data-start=\"1142\"\u003e120,000 ين ياباني شهريًا\u003c/strong\u003e طوال فترة المنحة (حتى سنتين كحد أقصى).\u003c/li\u003e\u003cli data-end=\"1288\" data-start=\"1214\"\u003eلا توجد رسوم دراسية إضافية، والمنحة تدعم الطالب في تخصصه الأكاديمي مباشرة.\u003c/li\u003e\u003c/ul\u003e\u003c/div\u003e\u003c/div\u003e"
                                },
                                {
                                    "header":  "معايير التقديم",
                                    "body":  "\u003cdiv bis_skin_checked=\"1\"\u003e\u003cdiv bis_skin_checked=\"1\" class=\"qualifications_ar\"\u003e\u003cul\u003e\u003cli data-end=\"1375\" data-start=\"1318\"\u003eأن يكون الطالب في \u003cstrong data-end=\"1372\" data-start=\"1336\"\u003eالسنة الأولى من برنامج الماجستير\u003c/strong\u003e.\u003c/li\u003e\u003cli data-end=\"1465\" data-start=\"1378\"\u003eأن ينتمي إلى واحدة من الدول المدرجة في القائمة (آسيا، أفريقيا، أمريكا الجنوبية، إلخ).\u003c/li\u003e\u003cli data-end=\"1566\" data-start=\"1468\"\u003eأن يكون تخصص الطالب مرتبطًا بمعالجة المعلومات والاتصالات، أو يستخدم هذا المجال ضمن بحثه الأكاديمي.\u003c/li\u003e\u003c/ul\u003e\u003c/div\u003e\u003c/div\u003e"
                                }
                            ]
           }
}