{
    "id":  "30218",
    "status":  "ok",
    "fetched_at":  "2026-06-10T23:48:53Z",
    "official_link":  null,
    "org_about":  "Orascom Construction Limited is a leading global engineering and construction contractor primarily focused on infrastructure, industrial and high-end commercial projects in the Middle East, North Africa, the United States, and the Pacific Rim for public and private clients. The Group also develops and invests in infrastructure opportunities.",
    "en":  {
               "lang":  "en",
               "title":  "Onsi Sawiris Scholarship 2026 for Egyptian Students Fully Funded Bachelor’s in USA",
               "sections":  [
                                {
                                    "header":  "Opportunity description",
                                    "body":  "\u003cdiv\u003e\u003cdiv class=\"description\"\u003e\u003cdiv\u003e\u003cdiv class=\"description\"\u003e\u003cdiv\u003e\u003cdiv class=\"description\"\u003e\u003cdiv\u003e\u003cdiv class=\"description\"\u003e\u003ch2\u003e\u003cspan\u003eThe Onsi Sawiris Scholarship Program, established by Orascom Construction, provides fully funded scholarships for Egyptian students to pursue their bachelor\u0026#39;s degrees at prestigious universities in the United States. The program aims to facilitate academic development, character building, and the economic prosperity of Egypt.\u003c/span\u003e\u003c/h2\u003e\u003cp data-path-to-node=\"12\"\u003e\u003cspan\u003eEndorsed Universities include:\u003c/span\u003e\u003c/p\u003e\u003cul data-path-to-node=\"13\"\u003e\u003cli\u003e\u003cp data-path-to-node=\"13,0,0\"\u003e\u003cspan\u003eUniversity of Chicago\u003c/span\u003e\u003c/p\u003e\u003c/li\u003e\u003cli\u003e\u003cp data-path-to-node=\"13,1,0\"\u003e\u003cspan\u003eStanford University\u003c/span\u003e\u003c/p\u003e\u003c/li\u003e\u003cli\u003e\u003cp data-path-to-node=\"13,2,0\"\u003e\u003cspan\u003eUniversity of Pennsylvania\u003c/span\u003e\u003c/p\u003e\u003c/li\u003e\u003cli\u003e\u003cp data-path-to-node=\"13,3,0\"\u003e\u003cspan\u003eHarvard University\u003c/span\u003e\u003c/p\u003e\u003c/li\u003e\u003cli\u003e\u003cp data-path-to-node=\"13,4,0\"\u003e\u003cspan\u003eMassachusetts Institute of Technology (MIT)\u003c/span\u003e\u003cbr\u003e\u003cbr\u003e\u003c/p\u003e\u003c/li\u003e\u003c/ul\u003e\u003cp data-path-to-node=\"13,4,0\"\u003e\u003cspan\u003e\u003cb data-index-in-node=\"0\" data-path-to-node=\"35,1,0\"\u003eFields Related:\u003c/b\u003e Engineering and Architecture, Business, Economics, Finance.\u003c/span\u003e\u003cbr\u003e\u003cb data-index-in-node=\"0\" data-path-to-node=\"2,0,0\"\u003e* Dual Nationality:\u003c/b\u003e Preference will be given to applicants who do not hold dual nationality.\u003c/p\u003e\u003cp data-path-to-node=\"3\"\u003e\u003cbr\u003e\u003c/p\u003e\u003c/div\u003e\u003c/div\u003e\u003c/div\u003e\u003c/div\u003e\u003c/div\u003e\u003c/div\u003e\u003c/div\u003e\u003c/div\u003e"
                                },
                                {
                                    "header":  "Benefits",
                                    "body":  "\u003cdiv\u003e\u003cdiv class=\"benefits\"\u003e\u003cdiv\u003e\u003cdiv class=\"benefits\"\u003e\u003cdiv\u003e\u003cdiv class=\"benefits\"\u003e\u003cdiv\u003e\u003cdiv class=\"benefits\"\u003e\u003cspan\u003eThe scholarship provides full tuition coverage, including:\u003c/span\u003e\u003cul data-path-to-node=\"16\"\u003e\u003cli\u003e\u003cp data-path-to-node=\"16,0,0\"\u003e\u003cspan\u003eFull tuition fees\u003c/span\u003e\u003c/p\u003e\u003c/li\u003e\u003cli\u003e\u003cp data-path-to-node=\"16,1,0\"\u003e\u003cspan\u003eTravel expenses\u003c/span\u003e\u003c/p\u003e\u003c/li\u003e\u003cli\u003e\u003cp data-path-to-node=\"16,2,0\"\u003e\u003cspan\u003eLiving allowance\u003c/span\u003e\u003c/p\u003e\u003c/li\u003e\u003cli\u003e\u003cp data-path-to-node=\"16,3,0\"\u003e\u003cspan\u003eBooks and computer\u003c/span\u003e\u003c/p\u003e\u003c/li\u003e\u003cli\u003e\u003cp data-path-to-node=\"16,4,0\"\u003e\u003cspan\u003eHealth insurance\u003c/span\u003e\u003c/p\u003e\u003c/li\u003e\u003c/ul\u003e\u003c/div\u003e\u003c/div\u003e\u003c/div\u003e\u003c/div\u003e\u003c/div\u003e\u003c/div\u003e\u003c/div\u003e\u003c/div\u003e"
                                },
                                {
                                    "header":  "Eligibility criteria",
                                    "body":  "\u003cdiv\u003e\u003cdiv class=\"qualifications\"\u003e\u003cdiv\u003e\u003cdiv class=\"qualifications\"\u003e\u003cdiv\u003e\u003cdiv class=\"qualifications\"\u003e\u003cdiv\u003e\u003cdiv class=\"qualifications\"\u003e\u003cul\u003e\u003cli\u003e\u003cp data-path-to-node=\"18,0,0\"\u003e\u003cb data-index-in-node=\"0\" data-path-to-node=\"18,0,0\"\u003e\u003cspan\u003eNationality:\u003c/span\u003e\u003c/b\u003e\u003cspan\u003e\u0026nbsp;Must be an Egyptian national and resident of Egypt (preference given to non-dual nationality holders).\u003c/span\u003e\u003c/p\u003e\u003c/li\u003e\u003cli\u003e\u003cp data-path-to-node=\"18,1,0\"\u003e\u003cspan\u003e\u003cb data-index-in-node=\"0\" data-path-to-node=\"18,1,0\"\u003eAge limit:\u003c/b\u003e Applicants must not exceed 19 years of age.\u003c/span\u003e\u003c/p\u003e\u003c/li\u003e\u003cli\u003e\u003cp data-path-to-node=\"18,2,0\"\u003e\u003cspan\u003e\u003cb data-index-in-node=\"0\" data-path-to-node=\"18,2,0\"\u003eAcademic Excellence:\u003c/b\u003e Cumulative GPA of 3.5 or 90% or equivalent in high school degrees.\u003c/span\u003e\u003c/p\u003e\u003c/li\u003e\u003cli\u003e\u003cp data-path-to-node=\"18,3,0\"\u003e\u003cspan\u003e\u003cb data-index-in-node=\"0\" data-path-to-node=\"18,3,0\"\u003eLanguage Proficiency:\u003c/b\u003e TOEFL iBT\u0026reg; minimum score of 100 OR IELTS (Academic) minimum score of 7.5, (Note: The test must have been taken within the last 2 years).\u003c/span\u003e\u003c/p\u003e\u003c/li\u003e\u003cli\u003e\u003cp data-path-to-node=\"18,4,0\"\u003e\u003cspan\u003e\u003cb data-index-in-node=\"0\" data-path-to-node=\"18,4,0\"\u003eStandardized Tests:\u003c/b\u003e Minimum SAT I score of 1450 OR Minimum ACT score of 32 (taken within 2 years).\u003c/span\u003e\u003c/p\u003e\u003c/li\u003e\u003cli\u003e\u003cp data-path-to-node=\"18,5,0\"\u003e\u003cspan\u003e\u003cb data-index-in-node=\"0\" data-path-to-node=\"18,5,0\"\u003eExtracurriculars:\u003c/b\u003e Must have a proven record of extracurricular activities.\u003c/span\u003e\u003c/p\u003e\u003c/li\u003e\u003cli\u003e\u003cp data-path-to-node=\"18,6,0\"\u003e\u003cspan\u003e\u003cb data-index-in-node=\"0\" data-path-to-node=\"18,6,0\"\u003eCommitment:\u003c/b\u003e Must be committed to returning to Egypt for two years directly after completing the bachelor\u0026#39;s degree.\u003c/span\u003e\u003c/p\u003e\u003c/li\u003e\u003cli\u003e\u003cp data-path-to-node=\"18,7,0\"\u003e\u003cspan\u003e\u003cb data-index-in-node=\"0\" data-path-to-node=\"18,7,0\"\u003eNote:\u003c/b\u003e Engineering programs cover specific fields like civil, environmental, energy, etc. Computer engineering/science are not funded as majors.\u003c/span\u003e\u003c/p\u003e\u003c/li\u003e\u003c/ul\u003e\u003c/div\u003e\u003c/div\u003e\u003c/div\u003e\u003c/div\u003e\u003c/div\u003e\u003c/div\u003e\u003c/div\u003e\u003c/div\u003e"
                                }
                            ]
           },
    "ar":  {
               "lang":  "ar",
               "title":  "منحة أنسي ساويرس للمصريين 2026 بكالوريوس في الولايات المتحدة بتمويل كامل",
               "sections":  [
                                {
                                    "header":  "وصف الفرصة",
                                    "body":  "\u003cdiv\u003e\u003cdiv class=\"description_ar\"\u003e\u003cdiv\u003e\u003cdiv class=\"description_ar\"\u003e\u003cdiv\u003e\u003cdiv class=\"description_ar\"\u003e\u003cdiv\u003e\u003cdiv class=\"description_ar\"\u003e\u003cp data-path-to-node=\"23\"\u003eيوفر برنامج منحة أنسي ساويرس، الذي أسسته شركة أوراسكوم للإنشاءات، منحاً دراسية ممولة بالكامل للطلاب المصريين لمتابعة درجة البكالوريوس في جامعات مرموقة في الولايات المتحدة الأمريكية. يهدف البرنامج إلى تعزيز التطور الأكاديمي، وبناء الشخصية، ودعم الازدهار الاقتصادي في مصر.\u003c/p\u003e\u003cp data-path-to-node=\"24\"\u003eالجامعات المعتمدة تشمل:\u003c/p\u003e\u003cul\u003e\u003cli\u003e\u003cp data-path-to-node=\"25,0,0\"\u003eجامعة شيكاغو\u003c/p\u003e\u003c/li\u003e\u003cli\u003e\u003cp data-path-to-node=\"25,1,0\"\u003eجامعة ستانفورد\u003c/p\u003e\u003c/li\u003e\u003cli\u003e\u003cp data-path-to-node=\"25,2,0\"\u003eجامعة بنسلفانيا\u003c/p\u003e\u003c/li\u003e\u003cli\u003e\u003cp data-path-to-node=\"25,3,0\"\u003eجامعة هارفارد\u003c/p\u003e\u003c/li\u003e\u003cli\u003e\u003cp data-path-to-node=\"25,4,0\"\u003eمعهد ماساتشوستس للتكنولوجيا (MIT)\u003cbr\u003e\u003cbr\u003e\u003c/p\u003e\u003cp data-path-to-node=\"1\"\u003e\u003cb data-index-in-node=\"0\" data-path-to-node=\"1\"\u003eالمجالات ذات الصلة: الهندسة والعمارة، الأعمال، الاقتصاد، والمالية.\u003c/b\u003e\u003c/p\u003e\u003c/li\u003e\u003c/ul\u003e\u003c/div\u003e\u003c/div\u003e\u003c/div\u003e\u003c/div\u003e\u003c/div\u003e\u003c/div\u003e\u003c/div\u003e\u003c/div\u003e"
                                },
                                {
                                    "header":  "المنافع والفوائد",
                                    "body":  "\u003cdiv\u003e\u003cdiv class=\"benefits_ar\"\u003e\u003cdiv\u003e\u003cdiv class=\"benefits_ar\"\u003e\u003cdiv\u003e\u003cdiv class=\"benefits_ar\"\u003e\u003cdiv\u003e\u003cdiv class=\"benefits_ar\"\u003eتوفر المنحة تغطية شاملة للرسوم الدراسية، وتشمل:\u003cul data-path-to-node=\"28\"\u003e\u003cli\u003e\u003cp data-path-to-node=\"28,0,0\"\u003eالرسوم الدراسية الكاملة\u003c/p\u003e\u003c/li\u003e\u003cli\u003e\u003cp data-path-to-node=\"28,1,0\"\u003eتكاليف السفر\u003c/p\u003e\u003c/li\u003e\u003cli\u003e\u003cp data-path-to-node=\"28,2,0\"\u003eبدل معيشة\u003c/p\u003e\u003c/li\u003e\u003cli\u003e\u003cp data-path-to-node=\"28,3,0\"\u003eالكتب وجهاز كمبيوتر\u003c/p\u003e\u003c/li\u003e\u003cli\u003e\u003cp data-path-to-node=\"28,4,0\"\u003eتأمين صحي وغيرها من الفوائد\u003c/p\u003e\u003c/li\u003e\u003c/ul\u003e\u003c/div\u003e\u003c/div\u003e\u003c/div\u003e\u003c/div\u003e\u003c/div\u003e\u003c/div\u003e\u003c/div\u003e\u003c/div\u003e"
                                },
                                {
                                    "header":  "معايير التقديم",
                                    "body":  "\u003cdiv\u003e\u003cdiv class=\"qualifications_ar\"\u003e\u003cdiv\u003e\u003cdiv class=\"qualifications_ar\"\u003e\u003cdiv\u003e\u003cdiv class=\"qualifications_ar\"\u003e\u003cdiv\u003e\u003cdiv class=\"qualifications_ar\"\u003e\u003cul\u003e\u003cli\u003e\u003cp data-path-to-node=\"30,0,0\"\u003e\u003cb data-index-in-node=\"0\" data-path-to-node=\"30,0,0\"\u003eالجنسية:\u003c/b\u003e يجب أن يكون المتقدم مصري الجنسية ومقيماً في مصر (تُعطى الأفضلية لمن لا يحملون جنسية مزدوجة).\u003c/p\u003e\u003c/li\u003e\u003cli\u003e\u003cp data-path-to-node=\"30,1,0\"\u003e\u003cb data-index-in-node=\"0\" data-path-to-node=\"30,1,0\"\u003eالعمر:\u003c/b\u003e يجب ألا يتجاوز عمر المتقدم 19 عاماً.\u003c/p\u003e\u003c/li\u003e\u003cli\u003e\u003cp data-path-to-node=\"30,2,0\"\u003e\u003cb data-index-in-node=\"0\" data-path-to-node=\"30,2,0\"\u003eالتفوق الأكاديمي:\u003c/b\u003e معدل تراكمي 3.5 أو 90% أو ما يعادلها في شهادة الثانوية.\u003c/p\u003e\u003c/li\u003e\u003cli\u003e\u003cp data-path-to-node=\"30,3,0\"\u003e\u003cb data-index-in-node=\"0\" data-path-to-node=\"30,3,0\"\u003eإتقان اللغة:\u003c/b\u003e الحصول على درجة 100 كحد أدنى في اختبار TOEFL iBT\u0026reg; أو 7.5 كحد أدنى في اختبار IELTS الأكاديمي, \u003cb data-index-in-node=\"0\" data-path-to-node=\"1\"\u003eملاحظة: يجب أن يكون الاختبار قد تم إجراؤه خلال العامين الماضيين.\u003c/b\u003e\u003c/p\u003e\u003c/li\u003e\u003cli\u003e\u003cp data-path-to-node=\"30,4,0\"\u003e\u003cb data-index-in-node=\"0\" data-path-to-node=\"30,4,0\"\u003eالاختبارات القياسية:\u003c/b\u003e الحصول على 1450 كحد أدنى في SAT I أو 32 كحد أدنى في ACT.\u003c/p\u003e\u003c/li\u003e\u003cli\u003e\u003cp data-path-to-node=\"30,5,0\"\u003e\u003cb data-index-in-node=\"0\" data-path-to-node=\"30,5,0\"\u003eالأنشطة اللامنهجية:\u003c/b\u003e يجب أن يكون للمتقدم مشاركات مُثبتة في الأنشطة اللامنهجية.\u003c/p\u003e\u003c/li\u003e\u003cli\u003e\u003cp data-path-to-node=\"30,6,0\"\u003e\u003cb data-index-in-node=\"0\" data-path-to-node=\"30,6,0\"\u003eالالتزام:\u003c/b\u003e يجب الالتزام بالعودة إلى مصر لمدة عامين فور الانتهاء من درجة البكالوريوس.\u003c/p\u003e\u003c/li\u003e\u003cli\u003e\u003cp data-path-to-node=\"30,7,0\"\u003e\u003cb data-index-in-node=\"0\" data-path-to-node=\"30,7,0\"\u003eملاحظة:\u003c/b\u003e برامج الهندسة تغطي تخصصات محددة (مثل المدنية والبيئية)؛ بينما لا يتم تمويل تخصصات هندسة وعلوم الحاسوب كتخصص رئيسي.\u003c/p\u003e\u003c/li\u003e\u003c/ul\u003e\u003c/div\u003e\u003c/div\u003e\u003c/div\u003e\u003c/div\u003e\u003c/div\u003e\u003c/div\u003e\u003c/div\u003e\u003c/div\u003e"
                                }
                            ]
           }
}