{
    "id":  "30969",
    "status":  "ok",
    "fetched_at":  "2026-06-10T23:50:17Z",
    "official_link":  null,
    "org_about":  "Established in 2006 by Nabil Boustany and his son Fadi, the Boustany Foundation is present in Switzerland and Monaco. Preceding the Foundation itself, the first Boustany Scholarship was awarded in 1997 to an MBA student at the University of Cambridge. The Foundation has since awarded many scholarships in various fields with plans to create more opportunities in the coming years for exceptional students.",
    "en":  {
               "lang":  "en",
               "title":  "Partially Funded Harvard MBA Scholarship 2026",
               "sections":  [
                                {
                                    "header":  "Opportunity description",
                                    "body":  "\u003cdiv\u003e\u003cdiv class=\"description\"\u003e\u003cdiv\u003e\u003cdiv class=\"description\"\u003e\u003cdiv\u003e\u003cdiv class=\"description\"\u003e\u003cdiv\u003e\u003cdiv class=\"description\"\u003e\u003cp\u003eThe Harvard University MBA Scholarship presented by the Boustany Foundation is a distinguished opportunity for exceptional international students granted admission to the Harvard Business School MBA, renowned as one of the world\u0026#39;s leading business programs. Offered every two years, this scholarship provides significant financial support coupled with a unique internship experience in Monaco.\u003c/p\u003e\u003ch2\u003eKey Responsibilities\u003c/h2\u003e\u003cul\u003e\u003cli\u003e75% tuition fee coverage for the Harvard MBA program.\u003c/li\u003e\u003cli\u003eTravel and accommodation expenses related to the mandatory internship in Monaco.\u003c/li\u003e\u003cli\u003eEngagement with international philanthropic and educational initiatives through the Boustany Foundation.\u003c/li\u003e\u003c/ul\u003e\u003c/div\u003e\u003c/div\u003e\u003c/div\u003e\u003c/div\u003e\u003c/div\u003e\u003c/div\u003e\u003c/div\u003e\u003c/div\u003e"
                                },
                                {
                                    "header":  "Benefits",
                                    "body":  "\u003cdiv\u003e\u003cdiv class=\"benefits\"\u003e\u003cdiv\u003e\u003cdiv class=\"benefits\"\u003e\u003cdiv\u003e\u003cdiv class=\"benefits\"\u003e\u003cdiv\u003e\u003cdiv class=\"benefits\"\u003e\u003cul\u003e\u003cli\u003e75% tuition fee coverage.\u003c/li\u003e\u003cli\u003eFull coverage of travel and accommodation expenses for the Monaco internship.\u003c/li\u003e\u003cli\u003eExposure to global educational and philanthropic initiatives.\u003c/li\u003e\u003c/ul\u003e\u003c/div\u003e\u003c/div\u003e\u003c/div\u003e\u003c/div\u003e\u003c/div\u003e\u003c/div\u003e\u003c/div\u003e\u003c/div\u003e"
                                },
                                {
                                    "header":  "Eligibility criteria",
                                    "body":  "\u003cdiv\u003e\u003cdiv class=\"qualifications\"\u003e\u003cdiv\u003e\u003cdiv class=\"qualifications\"\u003e\u003cdiv\u003e\u003cdiv class=\"qualifications\"\u003e\u003cdiv\u003e\u003cdiv class=\"qualifications\"\u003e\u003cul\u003e\u003cli\u003eExcellent academic background.\u003c/li\u003e\u003cli\u003eStrong leadership potential and promise.\u003c/li\u003e\u003cli\u003eOfficial offer from the Harvard MBA program.\u003c/li\u003e\u003cli\u003eCommit to a two-month unpaid internship with the Boustany Foundation.\u003c/li\u003e\u003c/ul\u003e\u003c/div\u003e\u003c/div\u003e\u003c/div\u003e\u003c/div\u003e\u003c/div\u003e\u003c/div\u003e\u003c/div\u003e\u003c/div\u003e"
                                }
                            ]
           },
    "ar":  {
               "lang":  "ar",
               "title":  "منحة دراسية جزئية لدراسة ماجستير إدارة الأعمال في هارفارد 2027",
               "sections":  [
                                {
                                    "header":  "وصف الفرصة",
                                    "body":  "\u003cdiv\u003e\u003cdiv class=\"description_ar\"\u003e\u003cdiv\u003e\u003cdiv class=\"description_ar\"\u003e\u003cdiv\u003e\u003cdiv class=\"description_ar\"\u003e\u003cdiv\u003e\u003cdiv class=\"description_ar\"\u003e\u003cp\u003eتُعتبَر منحة ماجستير إدارة الأعمال بجامعة هارفارد والمقدمة من مؤسسة البستاني واحدة من أكثر المنح الدراسية تميزًا في العالم، وهي تُقدم للطلاب الدوليين البارزين الذين تم قبولهم في برنامج ماجستير إدارة الأعمال في كلية هارفارد للأعمال، والمُصنف كواحد من أفضل برامج إدارة الأعمال في العالم. تتاح هذه المنحة كل عامين وتوفر تمويلًا قويًا بالإضافة إلى فرصة تدريب فريدة في موناكو.\u003c/p\u003e\u003ch2\u003eتفاصيل الفرصة\u003c/h2\u003e\u003cul\u003e\u003cli\u003eتغطية 75% من الرسوم الدراسية لماجستير إدارة الأعمال.\u003c/li\u003e\u003cli\u003eتغطية نفقات السفر والإقامة المتعلقة بالتدريب الإجباري في موناكو.\u003c/li\u003e\u003cli\u003eالانخراط في مبادرات عالمية خيرية وتعليمية تحت إشراف مؤسسة البستاني.\u003c/li\u003e\u003c/ul\u003e\u003ch2\u003eالتخصصات أو المجالات المتاحة\u003c/h2\u003e\u003cul\u003e\u003cli\u003eإدارة الأعمال وماجستير إدارة الأعمال.\u003c/li\u003e\u003c/ul\u003e\u003c/div\u003e\u003c/div\u003e\u003c/div\u003e\u003c/div\u003e\u003c/div\u003e\u003c/div\u003e\u003c/div\u003e\u003c/div\u003e"
                                },
                                {
                                    "header":  "المنافع والفوائد",
                                    "body":  "\u003cdiv\u003e\u003cdiv class=\"benefits_ar\"\u003e\u003cdiv\u003e\u003cdiv class=\"benefits_ar\"\u003e\u003cdiv\u003e\u003cdiv class=\"benefits_ar\"\u003e\u003cdiv\u003e\u003cdiv class=\"benefits_ar\"\u003e\u003cul\u003e\u003cli\u003eتغطية 75% من الرسوم الدراسية.\u003c/li\u003e\u003cli\u003eتغطية نفقات السفر والإقامة للتدريب في موناكو.\u003c/li\u003e\u003cli\u003eالتعرف على المبادرات التعليمية والخيرية العالمية.\u003c/li\u003e\u003c/ul\u003e\u003c/div\u003e\u003c/div\u003e\u003c/div\u003e\u003c/div\u003e\u003c/div\u003e\u003c/div\u003e\u003c/div\u003e\u003c/div\u003e"
                                },
                                {
                                    "header":  "معايير التقديم",
                                    "body":  "\u003cdiv\u003e\u003cdiv class=\"qualifications_ar\"\u003e\u003cdiv\u003e\u003cdiv class=\"qualifications_ar\"\u003e\u003cdiv\u003e\u003cdiv class=\"qualifications_ar\"\u003e\u003cdiv\u003e\u003cdiv class=\"qualifications_ar\"\u003e\u003cul\u003e\u003cli\u003eخبرة عملية قوية من 2-5 سنوات\u0026nbsp;\u003c/li\u003e\u003cli\u003eخلفية أكاديمية متميزة.\u003c/li\u003e\u003cli\u003eالإمكانيات القيادية الواضحة والوعود المستقبلية.\u003c/li\u003e\u003cli\u003eالقبول في برنامج الماجستير بجامعة هارفارد.\u003c/li\u003e\u003cli\u003eإكمال تدريب لمدة شهرين.\u003c/li\u003e\u003c/ul\u003e\u003c/div\u003e\u003c/div\u003e\u003c/div\u003e\u003c/div\u003e\u003c/div\u003e\u003c/div\u003e\u003c/div\u003e\u003c/div\u003e"
                                }
                            ]
           }
}